setup.py
dbpost/__init__.py
dbpost/client.py
dbpost/constants.py
dbpost/crypto_helper.py
dbpost/log.py
dbpost/server.py
dbpost/utils.py
dbpost.egg-info/PKG-INFO
dbpost.egg-info/SOURCES.txt
dbpost.egg-info/dependency_links.txt
dbpost.egg-info/requires.txt
dbpost.egg-info/top_level.txt
dbpost/bin/run_dbpost.py