Metadata-Version: 1.0
Name: dbpost
Version: 0.2.11
Summary: proxy for save db data. support mysql、sqlite、mongodb
Home-page: https://github.com/dantezhu/dbpost
Author: dantezhu
Author-email: zny2008@gmail.com
License: BSD
Platform: UNKNOWN
